iam_to_sqlite/__init__.py
iam_to_sqlite/cli.py
iam_to_sqlite-0.1.dist-info/LICENSE
iam_to_sqlite-0.1.dist-info/METADATA
iam_to_sqlite-0.1.dist-info/WHEEL
iam_to_sqlite-0.1.dist-info/entry_points.txt
iam_to_sqlite-0.1.dist-info/top_level.txt
iam_to_sqlite-0.1.dist-info/RECORD
