Metadata-Version: 2.1
Name: iam-to-sqlite
Version: 0.1
Summary: Load Amazon IAM data into a SQLite database
Home-page: https://github.com/simonw/iam-to-sqlite
Author: Simon Willison
License: Apache License, Version 2.0
Project-URL: Issues, https://github.com/simonw/iam-to-sqlite/issues
Project-URL: CI, https://github.com/simonw/iam-to-sqlite/actions
Project-URL: Changelog, https://github.com/simonw/iam-to-sqlite/releases
Platform: UNKNOWN
Requires-Python: >=3.6
Requires-Dist: click
Requires-Dist: sqlite-utils
Provides-Extra: test
Requires-Dist: pytest ; extra == 'test'
